{
    "abs": "ABS",
    "clearingHouse": "Clearing-House",
    "development": "DEVELOPEMENT",
    "training": "TRAINING",
    "home": "home",
    "about":    "about",
    "aboutAbsch": "About the ABSCH",
    "search":   "search",
    "submit":   "submit",
    "countryProfiles":  "Country Profiles",
    "help": "help",
    "forums": "forums",
    "records":  "Records",
    "nra": "National Report Analyzer",
    "countries":    "countries",
    "overviewAllCountries": "Overview - List all countries",
    "aboutNagoya": "About the Nagoya Protocol",
    "absch": "ABSCH",
    "accessBenefitSharing": "Access and Benefit-sharing",
    "kb":   "Knowledge Base",
    "faq": "FAQs",
    "trainingSite": "Training Site",
    "contactUs": "Contact us",
    "leaveTrainingSite": "Leave Training Site",
    "trainingMaterials": "Training Materials",
    "protocol": "Protocol",
    "nagoya": "Nagoya"
}